incubator/__init__.py
incubator/api.py
incubator/cli/__init__.py
incubator/cli/incubator.py
incubator/cli/types.py
incubator/core/__init__.py
incubator/core/build.py
incubator/core/caching.py
incubator/core/client.py
incubator/core/commands.py
incubator/core/config.py
incubator/core/constants.py
incubator/core/context.py
incubator/core/fileutils.py
incubator/core/history.py
incubator/core/layer.py
incubator/core/output.py
incubator/core/parsing.py
incubator/core/utilclasses.py
incubator/core/utils.py
incubator-0.9.0.dist-info/DESCRIPTION.rst
incubator-0.9.0.dist-info/METADATA
incubator-0.9.0.dist-info/RECORD
incubator-0.9.0.dist-info/WHEEL
incubator-0.9.0.dist-info/entry_points.txt
incubator-0.9.0.dist-info/metadata.json
incubator-0.9.0.dist-info/top_level.txt
