Metadata-Version: 2.0
Name: incubator
Version: 0.9.0
Summary: Python library for building container images.
Home-page: https://gitlab.com/lachmanfrantisek/incubator
Author: Frantisek Lachman
Author-email: lachmanfrantisek@gmail.com
License: MIT
Keywords: containers,build,docker,images
Platform: UNKNOWN
Classifier: Development Status :: 4 - Beta
Classifier: Environment :: Console
Classifier: Intended Audience :: Developers
Classifier: Intended Audience :: System Administrators
Classifier: License :: OSI Approved :: MIT License
Classifier: Operating System :: POSIX :: Linux
Classifier: Programming Language :: Python
Classifier: Programming Language :: Python :: 2.7
Classifier: Programming Language :: Python :: 3.4
Classifier: Programming Language :: Python :: 3.5
Classifier: Programming Language :: Python :: 3.6
Classifier: Programming Language :: Python :: Implementation :: CPython
Classifier: Topic :: Software Development :: Build Tools
Classifier: Topic :: Software Development :: Libraries :: Python Modules
Classifier: Topic :: System :: Software Distribution
Requires: dockerfile_parse
Requires: jsonschema
Requires: click
Requires: docker
Requires-Dist: click
Requires-Dist: docker (>=2.3.0)
Requires-Dist: dockerfile-parse (>=0.0.7)
Requires-Dist: jsonschema
